setup.py
axio_cli.egg-info/PKG-INFO
axio_cli.egg-info/SOURCES.txt
axio_cli.egg-info/dependency_links.txt
axio_cli.egg-info/entry_points.txt
axio_cli.egg-info/top_level.txt
axiolib/CHANGELOG.rst
axiolib/__init__.py
axiolib/app_profile.json
axiolib/cli_axio_launcher.py
axiolib/package.json
axiolib/axbuilder/project_run.py
axiolib/axbuilder/script_launcher.py
axiolib/axbuilder/tools/axiocpp.cp37-win_amd64.pyd
axiolib/axbuilder/tools/axiowinhooks.cp37-win_amd64.pyd
axiolib/axbuilder/tools/axmisc.cp37-win_amd64.pyd
axiolib/axbuilder/tools/nuitka.cp37-win_amd64.pyd
axiolib/axbuilder/tools/virtual_box.cp37-win_amd64.pyd
axiolib/bin/axio.cp37-win_amd64.pyd
axiolib/bin/builder_runner.exe
axiolib/bin/cli_axio.exe
axiolib/bin/python37.dll
axiolib/builders/application-1.0.0/axbuilder.cp37-win_amd64.pyd
axiolib/builders/application-1.0.0/axbuilder.json
axiolib/builders/axbuilder-1.6.0/axbuilder.cp37-win_amd64.pyd
axiolib/builders/axbuilder-1.6.0/axbuilder.json
axiolib/builders/board-1.0.0/axbuilder.cp37-win_amd64.pyd
axiolib/builders/board-1.0.0/axbuilder.json
axiolib/builders/component-1.0.0/axbuilder.cp37-win_amd64.pyd
axiolib/builders/component-1.0.0/axbuilder.json
axiolib/builders/custom-1.2.3/axbuilder.cp37-win_amd64.pyd
axiolib/builders/custom-1.2.3/axbuilder.json
axiolib/builders/framework-1.0.0/axbuilder.cp37-win_amd64.pyd
axiolib/builders/framework-1.0.0/axbuilder.json
axiolib/builders/package-2.0.0/axbuilder.cp37-win_amd64.pyd
axiolib/builders/package-2.0.0/axbuilder.json
axiolib/builders/package-2.0.0/builder_testsuite.py
axiolib/builders/package_manager-1.3.0/axbuilder.cp37-win_amd64.pyd
axiolib/builders/package_manager-1.3.0/axbuilder.json
axiolib/builders/platform-1.0.0/axbuilder.cp37-win_amd64.pyd
axiolib/builders/platform-1.0.0/axbuilder.json
axiolib/builders/rstdoc-1.5.1/CHANGELOG.rst
axiolib/builders/rstdoc-1.5.1/axbuilder.cp37-win_amd64.pyd
axiolib/builders/rstdoc-1.5.1/axbuilder.json
axiolib/builders/spawn-2.0.0/axbuilder.cp37-win_amd64.pyd
axiolib/builders/spawn-2.0.0/axbuilder.json
axiolib/builders/toolchain-1.0.0/axbuilder.cp37-win_amd64.pyd
axiolib/builders/toolchain-1.0.0/axbuilder.json
axiolib/data/axio.ico
axiolib/pysite-axio/importlib_metadata-2.0.0.dist-info/INSTALLER
axiolib/pysite-axio/importlib_metadata-2.0.0.dist-info/LICENSE
axiolib/pysite-axio/importlib_metadata-2.0.0.dist-info/METADATA
axiolib/pysite-axio/importlib_metadata-2.0.0.dist-info/RECORD
axiolib/pysite-axio/importlib_metadata-2.0.0.dist-info/WHEEL
axiolib/pysite-axio/importlib_metadata-2.0.0.dist-info/top_level.txt
axiolib/pysite-axio/mock-2.0.0.dist-info/DESCRIPTION.rst
axiolib/pysite-axio/mock-2.0.0.dist-info/INSTALLER
axiolib/pysite-axio/mock-2.0.0.dist-info/METADATA
axiolib/pysite-axio/mock-2.0.0.dist-info/RECORD
axiolib/pysite-axio/mock-2.0.0.dist-info/WHEEL
axiolib/pysite-axio/mock-2.0.0.dist-info/metadata.json
axiolib/pysite-axio/mock-2.0.0.dist-info/pbr.json
axiolib/pysite-axio/mock-2.0.0.dist-info/top_level.txt
axiolib/pysite-axio/py/_vendored_packages/apipkg-1.4.dist-info/DESCRIPTION.rst
axiolib/pysite-axio/py/_vendored_packages/apipkg-1.4.dist-info/INSTALLER
axiolib/pysite-axio/py/_vendored_packages/apipkg-1.4.dist-info/METADATA
axiolib/pysite-axio/py/_vendored_packages/apipkg-1.4.dist-info/RECORD
axiolib/pysite-axio/py/_vendored_packages/apipkg-1.4.dist-info/WHEEL
axiolib/pysite-axio/py/_vendored_packages/apipkg-1.4.dist-info/metadata.json
axiolib/pysite-axio/py/_vendored_packages/apipkg-1.4.dist-info/top_level.txt
axiolib/pysite-axio/py/_vendored_packages/iniconfig-1.0.0.dist-info/DESCRIPTION.rst
axiolib/pysite-axio/py/_vendored_packages/iniconfig-1.0.0.dist-info/INSTALLER
axiolib/pysite-axio/py/_vendored_packages/iniconfig-1.0.0.dist-info/METADATA
axiolib/pysite-axio/py/_vendored_packages/iniconfig-1.0.0.dist-info/RECORD
axiolib/pysite-axio/py/_vendored_packages/iniconfig-1.0.0.dist-info/WHEEL
axiolib/pysite-axio/py/_vendored_packages/iniconfig-1.0.0.dist-info/metadata.json
axiolib/pysite-axio/py/_vendored_packages/iniconfig-1.0.0.dist-info/top_level.txt
axiolib/pysite-axio/pytest-6.1.2.dist-info/INSTALLER
axiolib/pysite-axio/pytest-6.1.2.dist-info/LICENSE
axiolib/pysite-axio/pytest-6.1.2.dist-info/METADATA
axiolib/pysite-axio/pytest-6.1.2.dist-info/RECORD
axiolib/pysite-axio/pytest-6.1.2.dist-info/WHEEL
axiolib/pysite-axio/pytest-6.1.2.dist-info/entry_points.txt
axiolib/pysite-axio/pytest-6.1.2.dist-info/top_level.txt
axiolib/pysite-axio/pytest_cov-2.10.1.dist-info/AUTHORS.rst
axiolib/pysite-axio/pytest_cov-2.10.1.dist-info/INSTALLER
axiolib/pysite-axio/pytest_cov-2.10.1.dist-info/LICENSE
axiolib/pysite-axio/pytest_cov-2.10.1.dist-info/METADATA
axiolib/pysite-axio/pytest_cov-2.10.1.dist-info/RECORD
axiolib/pysite-axio/pytest_cov-2.10.1.dist-info/WHEEL
axiolib/pysite-axio/pytest_cov-2.10.1.dist-info/entry_points.txt
axiolib/pysite-axio/pytest_cov-2.10.1.dist-info/top_level.txt
axiolib/pysite-axio/pytest_html-2.1.1.dist-info/INSTALLER
axiolib/pysite-axio/pytest_html-2.1.1.dist-info/LICENSE
axiolib/pysite-axio/pytest_html-2.1.1.dist-info/METADATA
axiolib/pysite-axio/pytest_html-2.1.1.dist-info/RECORD
axiolib/pysite-axio/pytest_html-2.1.1.dist-info/WHEEL
axiolib/pysite-axio/pytest_html-2.1.1.dist-info/entry_points.txt
axiolib/pysite-axio/pytest_html-2.1.1.dist-info/top_level.txt
axiolib/pysite-axio/pytest_metadata-1.10.0.dist-info/AUTHORS
axiolib/pysite-axio/pytest_metadata-1.10.0.dist-info/INSTALLER
axiolib/pysite-axio/pytest_metadata-1.10.0.dist-info/LICENSE
axiolib/pysite-axio/pytest_metadata-1.10.0.dist-info/METADATA
axiolib/pysite-axio/pytest_metadata-1.10.0.dist-info/RECORD
axiolib/pysite-axio/pytest_metadata-1.10.0.dist-info/WHEEL
axiolib/pysite-axio/pytest_metadata-1.10.0.dist-info/entry_points.txt
axiolib/pysite-axio/pytest_metadata-1.10.0.dist-info/top_level.txt
axiolib/pysite-axio/pytest_mock-3.3.1.dist-info/INSTALLER
axiolib/pysite-axio/pytest_mock-3.3.1.dist-info/LICENSE
axiolib/pysite-axio/pytest_mock-3.3.1.dist-info/METADATA
axiolib/pysite-axio/pytest_mock-3.3.1.dist-info/RECORD
